AUTHORS
ChangeLog
LICENSE
README.md
requirements.txt
setup.cfg
setup.py
test-requirements.txt
tox.ini
doc/reqwise.png
reqwise/__init__.py
reqwise/cmd.py
reqwise/manager.py
reqwise/parse.py
reqwise/requirement.py
reqwise/result.py
reqwise.egg-info/PKG-INFO
reqwise.egg-info/SOURCES.txt
reqwise.egg-info/dependency_links.txt
reqwise.egg-info/entry_points.txt
reqwise.egg-info/not-zip-safe
reqwise.egg-info/pbr.json
reqwise.egg-info/requires.txt
reqwise.egg-info/top_level.txt
reqwise/common/__init__.py
reqwise/common/constants.py
reqwise/common/utils.py
reqwise/sources/__init__.py
reqwise/sources/copr.py
reqwise/sources/koji.py
reqwise/sources/source.py
reqwise/sources/yum.py
tests/base.py